{
    "styles": [
        {
            "src": "assets/img/styles-5.jpg",
            "title": "Пастелью",
            "link": "#pastel"
        },
        {
            "src": "assets/img/styles-6.jpg",
            "title": "Поп-арт",
            "link": "#popart"
        },
        {
            "src": "assets/img/styles-7.png",
            "title": "Фотомозаика",
            "link": "#mozaika"
        },
        {
            "src": "assets/img/styles-8.jpg",
            "title": "Шарж",
            "link": "#sharj"
        }
    ],
    "size": [
        {
            "small": "500",
            "middle": "1000",
            "large": "1500",
            "extra": "2000"
        }
    ],
    "material": [
        {
            "fiber": "500",
            "linen": "1000",
            "cotton": "500"
        }
    ]
}